funapi/__init__.py
funos-0.0.1.dist-info/LICENSE
funos-0.0.1.dist-info/METADATA
funos-0.0.1.dist-info/WHEEL
funos-0.0.1.dist-info/entry_points.txt
funos-0.0.1.dist-info/top_level.txt
funos-0.0.1.dist-info/RECORD
